pura/__init__.py
pura/balance.py
pura/compound.py
pura/data/pura.db
pura/reaction.py
pura/resolvers.py
pura/services/__init__.py
pura/services/cas.py
pura/services/chemspider.py
pura/services/cir.py
pura/services/db.py
pura/services/opsin.py
pura/services/pubchem.py
pura/services/service.py
pura/services/stout.py
pura/units.py
pura/utils.py
pura-0.2.4.dist-info/LICENSE
pura-0.2.4.dist-info/WHEEL
pura-0.2.4.dist-info/METADATA
pura-0.2.4.dist-info/RECORD
